memoize.py
setup.py
memoize.egg-info/PKG-INFO
memoize.egg-info/SOURCES.txt
memoize.egg-info/dependency_links.txt
memoize.egg-info/top_level.txt