Metadata-Version: 1.0
Name: memoize
Version: 1.0.0
Summary: Create properties that are only computed the first time they are called.
Home-page: https://github.com/sionide21/memoize
Author: Ben Olive
Author-email: sionide21@gmail.com
License: MIT
Platform: all
Classifier: Development Status :: 5 - Production/Stable
Classifier: Intended Audience :: Developers
Classifier: Operating System :: OS Independent
Classifier: License :: OSI Approved :: MIT License
Classifier: Topic :: Software Development :: Libraries :: Python Modules
